image_processing_framework/__init__.py
image_processing_framework/color_terminal.py
image_processing_framework/core.py
simple_image_framework-0.0.1.dist-info/METADATA
simple_image_framework-0.0.1.dist-info/WHEEL
simple_image_framework-0.0.1.dist-info/licenses/LICENSE
simple_image_framework-0.0.1.dist-info/RECORD
