Metadata-Version: 2.1
Name: simple-image-framework
Version: 0.0.1
Summary: A simple image framework, for digital image processing support on lab. 
Author-email: Cutie Deng <Dengzr2020@mail.sustech.edu.cn>
License-Expression: MIT
License-File: LICENSE
Classifier: License :: OSI Approved :: MIT License
Classifier: Operating System :: OS Independent
Classifier: Programming Language :: Python :: 3
Requires-Python: >=3.7
Requires-Dist: pillow
